{
  "date": "2026-01-26",
  "items": [
    {
      "type": "Birth",
      "year": "1958",
      "text": "Anita Baker, American singer-songwriter"
    },
    {
      "type": "Birth",
      "year": "1986",
      "text": "Mustapha Yatabaré, French-Malian footballer"
    },
    {
      "type": "Event",
      "year": "1934",
      "text": "The Apollo Theater reopens in Harlem, New York City."
    },
    {
      "type": "Birth",
      "year": "1983",
      "text": "Eric Werner, American ice hockey player"
    },
    {
      "type": "Event",
      "year": "1870",
      "text": "Reconstruction Era: Virginia is readmitted to the Union."
    },
    {
      "type": "Event",
      "year": "1856",
      "text": "First Battle of Seattle: Marines from the USS Decatur drive off Native American attackers after all-day battle with settlers."
    },
    {
      "type": "Death",
      "year": "1990",
      "text": "Lewis Mumford, American sociologist and historian (born 1895)"
    },
    {
      "type": "Event",
      "year": "1863",
      "text": "American Civil War: General Ambrose Burnside is relieved of command of the Army of the Potomac after the disastrous Fredericksburg campaign. He is replaced by Joseph Hooker."
    },
    {
      "type": "Birth",
      "year": "1994",
      "text": "Montrezl Harrell, American basketball player"
    },
    {
      "type": "Birth",
      "year": "1863",
      "text": "Charles Wade, Australian politician, 17th Premier of New South Wales (died 1922)"
    },
    {
      "type": "Birth",
      "year": "1984",
      "text": "Ryan Hoffman, Australian rugby league player"
    },
    {
      "type": "Birth",
      "year": "1988",
      "text": "Dan Bailey, American football player"
    },
    {
      "type": "Birth",
      "year": "1887",
      "text": "Marc Mitscher, American admiral and pilot (died 1947)"
    },
    {
      "type": "Event",
      "year": "1952",
      "text": "Black Saturday in Egypt: rioters burn Cairo's central business district, targeting British and upper-class Egyptian businesses."
    },
    {
      "type": "Birth",
      "year": "1949",
      "text": "Jonathan Carroll, American author"
    },
    {
      "type": "Birth",
      "year": "1990",
      "text": "Brandon Bolden, American football player"
    },
    {
      "type": "Death",
      "year": "1886",
      "text": "David Rice Atchison, American general and politician (born 1807)"
    },
    {
      "type": "Event",
      "year": "1918",
      "text": "Finnish Civil War: A group of Red Guards hangs a red lantern atop the tower of Helsinki Workers' Hall to symbolically mark the start of the war."
    },
    {
      "type": "Birth",
      "year": "1953",
      "text": "Anders Fogh Rasmussen, Danish politician and diplomat, 39th Prime Minister of Denmark"
    },
    {
      "type": "Birth",
      "year": "1991",
      "text": "Manti Te'o, American football player"
    },
    {
      "type": "Death",
      "year": "2017",
      "text": "Barbara Hale, American actress (born 1922)"
    },
    {
      "type": "Event",
      "year": "1950",
      "text": "The Constitution of India comes into force, forming a republic. Rajendra Prasad is sworn in as the first President of India. Observed as Republic Day in India."
    },
    {
      "type": "Birth",
      "year": "1905",
      "text": "Charles Lane, American actor and singer (died 2007)"
    },
    {
      "type": "Birth",
      "year": "1924",
      "text": "Anahid Ajemian, American violinist (died 2016)"
    },
    {
      "type": "Event",
      "year": "1998",
      "text": "Lewinsky scandal: On American television, U.S. President Bill Clinton denies having had \"sexual relations\" with former White House intern Monica Lewinsky."
    },
    {
      "type": "Birth",
      "year": "1977",
      "text": "Vince Carter, American basketball player"
    },
    {
      "type": "Event",
      "year": "1930",
      "text": "The Indian National Congress declares 26 January as Independence Day or as the day for Poorna Swaraj (\"Complete Independence\") which occurred 17 years later."
    },
    {
      "type": "Event",
      "year": "1915",
      "text": "The Rocky Mountain National Park is established by an act of the U.S. Congress."
    },
    {
      "type": "Event",
      "year": "1564",
      "text": "The Grand Duchy of Lithuania defeats the Tsardom of Russia in the Battle of Ula during the Livonian War."
    },
    {
      "type": "Event",
      "year": "1531",
      "text": "The 6.4–7.1 Mw Lisbon earthquake kills about thirty thousand people."
    },
    {
      "type": "Birth",
      "year": "1938",
      "text": "Henry Jaglom, English-American director and screenwriter (died 2025)"
    },
    {
      "type": "Birth",
      "year": "1955",
      "text": "Eddie Van Halen, Dutch-American guitarist, songwriter, and producer (died 2020)"
    },
    {
      "type": "Birth",
      "year": "1966",
      "text": "Kazushige Nagashima, Japanese baseball player and sportscaster"
    },
    {
      "type": "Event",
      "year": "1966",
      "text": "The three Beaumont children disappear from a beach in Glenelg, South Australia, resulting in one of the country's largest-ever police investigations."
    },
    {
      "type": "Event",
      "year": "1855",
      "text": "Point No Point Treaty is signed in Washington Territory."
    },
    {
      "type": "Birth",
      "year": "1924",
      "text": "Annette Strauss, American philanthropist and politician, Mayor of Dallas (died 1998)"
    },
    {
      "type": "Birth",
      "year": "1954",
      "text": "Kim Hughes, Australian cricketer"
    },
    {
      "type": "Event",
      "year": "2020",
      "text": "A Sikorsky S-76B flying from John Wayne Airport to Camarillo Airport crashes in Calabasas, 30 miles west of Los Angeles, killing all nine people on board, including five-time NBA champion Kobe Bryant and his daughter Gianna Bryant."
    },
    {
      "type": "Event",
      "year": "1986",
      "text": "The Ugandan government of Tito Okello is overthrown by the National Resistance Army, led by Yoweri Museveni."
    },
    {
      "type": "Birth",
      "year": "1935",
      "text": "Henry Jordan, American football player (died 1977)"
    },
    {
      "type": "Birth",
      "year": "1908",
      "text": "Robert Halperin, American yachtsman (died 1985)"
    },
    {
      "type": "Birth",
      "year": "1977",
      "text": "Justin Gimelstob, American tennis player and coach"
    },
    {
      "type": "Event",
      "year": "1861",
      "text": "American Civil War: The state of Louisiana secedes from the Union."
    },
    {
      "type": "Birth",
      "year": "1934",
      "text": "Roger Landry, Canadian businessman and publisher (died 2020)"
    },
    {
      "type": "Birth",
      "year": "1891",
      "text": "Wilder Penfield, American-Canadian neurosurgeon and academic (died 1976)"
    },
    {
      "type": "Event",
      "year": "2015",
      "text": "Syrian civil war: The People's Protection Units (YPG) recaptures the city of Kobanî from the Islamic State of Iraq and the Levant (ISIL), marking a turning point in the Siege of Kobanî."
    },
    {
      "type": "Event",
      "year": "1788",
      "text": "The British First Fleet, led by Arthur Phillip, sails into Port Jackson (Sydney Harbour) to establish Sydney, the first permanent European settlement on Australia. Commemorated as Australia Day."
    },
    {
      "type": "Event",
      "year": "1837",
      "text": "Michigan is admitted as the 26th U.S. state."
    },
    {
      "type": "Birth",
      "year": "1907",
      "text": "Rex Connor, Australian politician (died 1977)"
    },
    {
      "type": "Birth",
      "year": "1986",
      "text": "Gerald Green, American basketball player"
    },
    {
      "type": "Birth",
      "year": "1926",
      "text": "Joseph Bacon Fraser Jr., American architect and businessman, co-founded the Sea Pines Company (died 2014)"
    },
    {
      "type": "Birth",
      "year": "1973",
      "text": "Mayu Shinjo, Japanese author and illustrator"
    },
    {
      "type": "Birth",
      "year": "1947",
      "text": "Richard Portnow, American actor"
    },
    {
      "type": "Event",
      "year": "1942",
      "text": "World War II: The first United States forces arrive in Europe, landing in Northern Ireland."
    },
    {
      "type": "Birth",
      "year": "1992",
      "text": "Mercedes Moné, American wrestler"
    },
    {
      "type": "Event",
      "year": "1939",
      "text": "Spanish Civil War: Catalonia Offensive: Troops loyal to nationalist General Francisco Franco and aided by Italy take Barcelona."
    },
    {
      "type": "Event",
      "year": "1863",
      "text": "American Civil War: Governor of Massachusetts John Albion Andrew receives permission from the Secretary of War to raise a militia organization for men of African descent."
    },
    {
      "type": "Event",
      "year": "1959",
      "text": "The 41-acre (17 ha) Chain Island is listed for sale by the California State Lands Commission, with a minimum bid of $5,226."
    },
    {
      "type": "Birth",
      "year": "1958",
      "text": "Ellen DeGeneres, American comedian, actress, and talk show host"
    },
    {
      "type": "Event",
      "year": "1564",
      "text": "The Council of Trent establishes an official distinction between Roman Catholicism and Protestantism."
    }
  ],
  "source": "Wikipedia"
}